pypythia/__init__.py
pypythia/config.py
pypythia/custom_errors.py
pypythia/custom_types.py
pypythia/logger.py
pypythia/main.py
pypythia/msa.py
pypythia/prediction.py
pypythia/predictor.py
pypythia/raxmlng.py
pypythia/predictors/README.md
pypythia/predictors/latest.txt
pypythia/predictors/pythia_200.txt
pythiaphylopredictor-2.0.0.dist-info/METADATA
pythiaphylopredictor-2.0.0.dist-info/WHEEL
pythiaphylopredictor-2.0.0.dist-info/entry_points.txt
pythiaphylopredictor-2.0.0.dist-info/licenses/LICENSE
pythiaphylopredictor-2.0.0.dist-info/RECORD
