Metadata-Version: 2.4
Name: PythiaPhyloPredictor
Version: 2.0.0
Summary: Lightweight python library for predicting the difficulty of alignments in phylogenetics
Project-URL: Homepage, https://github.com/tschuelia/PyPythia
Project-URL: Documentation, https://tschuelia.github.io/PyPythia/latest/
Author-email: Julia Haag <info@juliaschmid.com>
License-Expression: GPL-3.0-or-later
License-File: LICENSE
Classifier: Programming Language :: Python :: 3.9
Classifier: Programming Language :: Python :: 3.10
Classifier: Programming Language :: Python :: 3.11
Classifier: Programming Language :: Python :: 3.12
Requires-Python: <3.13,>=3.9
Requires-Dist: biopython
Requires-Dist: lightgbm>=4.4
Requires-Dist: loguru
Requires-Dist: matplotlib
Requires-Dist: numpy>=2.0
Requires-Dist: pandas
Requires-Dist: shap>=0.41
Provides-Extra: test
Requires-Dist: pyarrow; extra == 'test'
Requires-Dist: pytest; extra == 'test'
